<?xml version="1.0"?>
<ListOrderItemsResponse xmlns="https://mws.amazonservices.com/Orders/2013-09-01">
  <ListOrderItemsResult>
    <OrderItems>
      <OrderItem>
        <QuantityOrdered>1</QuantityOrdered>
        <Title>Funko - Fun5222 - Pop - The Fifth Element - Diva Plavalaguna</Title>
        <ShippingTax>
          <CurrencyCode>EUR</CurrencyCode>
          <Amount>0.00</Amount>
        </ShippingTax>
        <PromotionDiscount>
          <CurrencyCode>EUR</CurrencyCode>
          <Amount>0.00</Amount>
        </PromotionDiscount>
        <ASIN>B00VQSQ040</ASIN>
        <SellerSKU>0849803052225</SellerSKU>
        <OrderItemId>57080400659179</OrderItemId>
        <QuantityShipped>1</QuantityShipped>
        <ShippingPrice>
          <CurrencyCode>EUR</CurrencyCode>
          <Amount>2.79</Amount>
        </ShippingPrice>
        <ItemPrice>
          <CurrencyCode>EUR</CurrencyCode>
          <Amount>18.40</Amount>
        </ItemPrice>
        <ItemTax>
          <CurrencyCode>EUR</CurrencyCode>
          <Amount>0.00</Amount>
        </ItemTax>
        <ShippingDiscount>
          <CurrencyCode>EUR</CurrencyCode>
          <Amount>0.00</Amount>
        </ShippingDiscount>
      </OrderItem>
    </OrderItems>
    <AmazonOrderId>404-5148226-1627558</AmazonOrderId>
  </ListOrderItemsResult>
  <ResponseMetadata>
    <RequestId>fad34685-00e9-4ba4-a870-cc187811fccf</RequestId>
  </ResponseMetadata>
</ListOrderItemsResponse>
